pytest_brightest/__init__.py
pytest_brightest/constants.py
pytest_brightest/plugin.py
pytest_brightest/reorder.py
pytest_brightest/shuffler.py
pytest_brightest-0.1.0.dist-info/METADATA
pytest_brightest-0.1.0.dist-info/WHEEL
pytest_brightest-0.1.0.dist-info/entry_points.txt
pytest_brightest-0.1.0.dist-info/RECORD
