Metadata-Version: 2.4
Name: pytest-brightest
Version: 0.1.0
Summary: Bright ideas for improving your pytest experience
Author-email: "Gregory M. Kapfhammer" <gkapfham@allegheny.edu>
Keywords: llm,pytest,testing
Classifier: Development Status :: 3 - Alpha
Classifier: Framework :: Pytest
Classifier: Intended Audience :: Developers
Classifier: License :: OSI Approved :: MIT License
Classifier: Operating System :: OS Independent
Classifier: Programming Language :: Python
Classifier: Programming Language :: Python :: 3
Classifier: Programming Language :: Python :: 3.11
Classifier: Programming Language :: Python :: 3.12
Classifier: Programming Language :: Python :: 3.13
Classifier: Topic :: Software Development :: Testing
Requires-Python: >=3.11
Requires-Dist: pytest-json-report>=1.5.0
Requires-Dist: pytest>=8.4.1
Requires-Dist: rich>=14.0.0
